cakesrt2audio/__init__.py
cakesrt2audio/__main__.py
cakesrt2audio/core.py
cakesrt2audio-0.2.0.dist-info/licenses/LICENSE
cakesrt2audio-0.2.0.dist-info/METADATA
cakesrt2audio-0.2.0.dist-info/WHEEL
cakesrt2audio-0.2.0.dist-info/entry_points.txt
cakesrt2audio-0.2.0.dist-info/top_level.txt
cakesrt2audio-0.2.0.dist-info/RECORD
