Metadata-Version: 2.4
Name: cakesrt2audio
Version: 0.2.0
Summary: Generate audio from SRT files using Microsoft Edge's text-to-speech service
Author-email: test <test@example.com>
License-Expression: MIT
Project-URL: Homepage, https://github.com/test/cakesrt2audio
Project-URL: Bug Tracker, https://github.com/test/cakesrt2audio/issues
Project-URL: Repository, https://github.com/test/cakesrt2audio
Keywords: tts,srt,subtitle,audio,speech-synthesis,edge-tts
Classifier: Development Status :: 4 - Beta
Classifier: Intended Audience :: Developers
Classifier: Topic :: Multimedia :: Sound/Audio :: Speech
Classifier: Topic :: Software Development :: Libraries :: Python Modules
Classifier: Programming Language :: Python :: 3
Classifier: Programming Language :: Python :: 3.8
Classifier: Programming Language :: Python :: 3.9
Classifier: Programming Language :: Python :: 3.10
Classifier: Programming Language :: Python :: 3.11
Classifier: Programming Language :: Python :: 3.12
Classifier: Operating System :: OS Independent
Requires-Python: >=3.8
License-File: LICENSE
Requires-Dist: edge-tts
Requires-Dist: pydub
Requires-Dist: srt
Requires-Dist: rich
Dynamic: license-file
